erkc/__init__.py
erkc/__main__.py
erkc/account.py
erkc/accrual.py
erkc/bills.py
erkc/client.py
erkc/errors.py
erkc/meters.py
erkc/paid.png
erkc/payment.py
erkc/utils.py
erkc-0.1.0.dist-info/LICENSE
erkc-0.1.0.dist-info/METADATA
erkc-0.1.0.dist-info/WHEEL
erkc-0.1.0.dist-info/RECORD
